CHANGELOG.rst
LICENSE
MANIFEST.in
README.rst
setup.cfg
setup.py
WordEmbeddingLoader.egg-info/PKG-INFO
WordEmbeddingLoader.egg-info/SOURCES.txt
WordEmbeddingLoader.egg-info/dependency_links.txt
WordEmbeddingLoader.egg-info/entry_points.txt
WordEmbeddingLoader.egg-info/requires.txt
WordEmbeddingLoader.egg-info/top_level.txt
doc/source/conf.py
doc/source/index.rst
test/word_embedding_loader/conftest.py
test/word_embedding_loader/test_cli.py
test/word_embedding_loader/test_word_embedding.py
test/word_embedding_loader/word2vec.bin
test/word_embedding_loader/loader/test_loader_common.py
test/word_embedding_loader/loader/test_loader_glove.py
test/word_embedding_loader/loader/test_loader_vocab.py
test/word_embedding_loader/loader/test_loader_word2vec_bin.py
test/word_embedding_loader/loader/test_loader_word2vec_text.py
test/word_embedding_loader/saver/test_saver.py
word_embedding_loader/__init__.py
word_embedding_loader/_version.py
word_embedding_loader/cli.py
word_embedding_loader/exceptions.py
word_embedding_loader/word_embedding.py
word_embedding_loader/loader/__init__.py
word_embedding_loader/loader/glove.py
word_embedding_loader/loader/vocab.py
word_embedding_loader/loader/word2vec_bin.cpp
word_embedding_loader/loader/word2vec_bin.pyx
word_embedding_loader/loader/word2vec_text.py
word_embedding_loader/saver/__init__.py
word_embedding_loader/saver/glove.py
word_embedding_loader/saver/numpy.py
word_embedding_loader/saver/word2vec_bin.cpp
word_embedding_loader/saver/word2vec_bin.pyx
word_embedding_loader/saver/word2vec_text.py